sitemap_mcp_server/__init__.py
sitemap_mcp_server/__main__.py
sitemap_mcp_server/config.py
sitemap_mcp_server/server.py
sitemap_mcp_server/utils.py
sitemap_mcp_server/prompts/__init__.py
sitemap_mcp_server/prompts/prompt_definitions.py
iflow_mcp_sitemap_mcp_server-0.1.3.dist-info/METADATA
iflow_mcp_sitemap_mcp_server-0.1.3.dist-info/WHEEL
iflow_mcp_sitemap_mcp_server-0.1.3.dist-info/entry_points.txt
iflow_mcp_sitemap_mcp_server-0.1.3.dist-info/RECORD
