Metadata-Version: 2.4
Name: iflow-mcp_sitemap-mcp-server
Version: 0.1.3
Summary: Sitemap MCP is a Model Context Protocol (MCP) server for fetching, parsing, analyzing, and visualizing website sitemaps
Project-URL: Repository, https://github.com/mugoosse/sitemap-mcp-server.git
Author-email: Maxime Goossens <mcp@mgo.rodeo>
License-Expression: MIT
Keywords: mcp,model-context-protocol,parser,sitemap,visualization,web-scraping,website-analysis,xml
Classifier: Development Status :: 4 - Beta
Classifier: Programming Language :: Python
Classifier: Topic :: Software Development :: Libraries :: Python Modules
Requires-Python: >=3.11
Requires-Dist: mcp[cli]>=1.6.0
Requires-Dist: pydantic>=2.11.3
Requires-Dist: ultimate-sitemap-parser>=1.3.1
Provides-Extra: dev
Requires-Dist: black>=25.1.0; extra == 'dev'
Requires-Dist: build>=1.2.2.post1; extra == 'dev'
Requires-Dist: twine>=6.1.0; extra == 'dev'
Provides-Extra: test
Requires-Dist: pytest-asyncio>=0.21.0; extra == 'test'
Requires-Dist: pytest>=7.3.1; extra == 'test'
